ab/__init__.py
ab/admin.py
ab/apps.py
ab/models.py
ab/utils.py
ab/migrations/__init__.py
django_AB_project-1.1.0.dist-info/DESCRIPTION.rst
django_AB_project-1.1.0.dist-info/METADATA
django_AB_project-1.1.0.dist-info/RECORD
django_AB_project-1.1.0.dist-info/WHEEL
django_AB_project-1.1.0.dist-info/metadata.json
django_AB_project-1.1.0.dist-info/top_level.txt
