Metadata-Version: 2.0
Name: django-AB-project
Version: 1.1.0
Summary: Simple and easy-to-use project for A/B testing.
Home-page: https://github.com/Vadim-Karpenko/django-AB-project
Author: Vadim Karpenko
Author-email: j.rell@protonmail.com
License: MIT
Platform: UNKNOWN
